conveyor/__init__.py
conveyor/context.py
conveyor/decorators.py
conveyor/error_handling.py
conveyor/pipeline.py
conveyor/stream.py
conveyor/tasks.py
conveyor_streaming-1.2.1.dist-info/METADATA
conveyor_streaming-1.2.1.dist-info/WHEEL
conveyor_streaming-1.2.1.dist-info/RECORD
