Metadata-Version: 2.3
Name: conveyor-streaming
Version: 1.2.1
Summary: A Python library for streamlining asynchronous streaming tasks and pipelines.
License: MIT
Keywords: async,streaming,pipeline,data processing
Author: ju-bezdek
Author-email: juraj.bezdek@gmail.com
Requires-Python: >=3.11,<4.0
Classifier: License :: OSI Approved :: MIT License
Classifier: Programming Language :: Python :: 3
Classifier: Programming Language :: Python :: 3.11
Classifier: Programming Language :: Python :: 3.12
Classifier: Programming Language :: Python :: 3.13
Project-URL: Documentation, https://conveyor-streaming.readthedocs.io/
Project-URL: Repository, https://github.com/ju-bezdek/conveyor
